extra_checks/__init__.py
extra_checks/apps.py
extra_checks/check_id.py
extra_checks/forms.py
extra_checks/py.typed
extra_checks/registry.py
extra_checks/utils.py
extra_checks/ast/__init__.py
extra_checks/ast/ast.py
extra_checks/ast/exceptions.py
extra_checks/ast/protocols.py
extra_checks/ast/source_provider.py
extra_checks/checks/__init__.py
extra_checks/checks/base_checks.py
extra_checks/checks/drf_serializer_checks.py
extra_checks/checks/model_checks.py
extra_checks/checks/model_field_checks.py
extra_checks/checks/self_checks.py
django_extra_checks-0.16.1.dist-info/METADATA
django_extra_checks-0.16.1.dist-info/WHEEL
django_extra_checks-0.16.1.dist-info/licenses/LICENSE
django_extra_checks-0.16.1.dist-info/RECORD
