Metadata-Version: 2.3
Name: django-extra-checks
Version: 0.16.1
Summary: Collection of useful checks for Django Checks Framework
Project-URL: Homepage, https://github.com/kalekseev/django-extra-checks
Author-email: Konstantin Alekseev <mail@kalekseev.com>
License: MIT
Keywords: checks,django
Classifier: Development Status :: 4 - Beta
Classifier: Environment :: Web Environment
Classifier: Framework :: Django
Classifier: Framework :: Django :: 4.2
Classifier: Framework :: Django :: 5.0
Classifier: Framework :: Django :: 5.1
Classifier: Intended Audience :: Developers
Classifier: License :: OSI Approved :: MIT License
Classifier: Operating System :: OS Independent
Classifier: Programming Language :: Python
Classifier: Programming Language :: Python :: 3
Classifier: Programming Language :: Python :: 3.8
Classifier: Programming Language :: Python :: 3.9
Classifier: Programming Language :: Python :: 3.10
Classifier: Programming Language :: Python :: 3.11
Classifier: Programming Language :: Python :: 3.12
Classifier: Programming Language :: Python :: 3.13
Requires-Python: >=3.8
Provides-Extra: dev
Requires-Dist: django; extra == 'dev'
Requires-Dist: django-stubs; extra == 'dev'
Requires-Dist: djangorestframework; extra == 'dev'
Requires-Dist: djangorestframework-stubs; extra == 'dev'
Requires-Dist: mypy; extra == 'dev'
Requires-Dist: pdbpp; extra == 'dev'
Requires-Dist: pre-commit; extra == 'dev'
Requires-Dist: ruff; extra == 'dev'
Provides-Extra: test
Requires-Dist: pytest; extra == 'test'
Requires-Dist: pytest-cov; extra == 'test'
Requires-Dist: pytest-django; extra == 'test'
